mansai/__init__.py
mansai/hello.py
mansai/cli/member.py
mansai/inner/deep_hello.py
mansai-0.1.10.data/data/table.csv
mansai-0.1.10.dist-info/entry_points.txt
mansai-0.1.10.dist-info/WHEEL
mansai-0.1.10.dist-info/METADATA
mansai-0.1.10.dist-info/RECORD
