Metadata-Version: 2.1
Name: mansai
Version: 0.1.10
Summary: Prank package for SAI circle in Sejong University
Author-email: Janghoo Lee <dlwkdgn1@naver.com>
Requires-Python: >=3.8
Requires-Dist: click
Requires-Dist: pytest ; extra == "dev"
Provides-Extra: dev
